arraycontract/__init__.py
arraycontract/common.py
arraycontract/dtype_contract.py
arraycontract/ndim_contract.py
arraycontract/shape_contract.py
tests/__init__.py
tests/test_dtype.py
tests/test_ndim.py
tests/test_shape.py
arraycontract-0.0.2.dist-info/METADATA
arraycontract-0.0.2.dist-info/WHEEL
arraycontract-0.0.2.dist-info/top_level.txt
arraycontract-0.0.2.dist-info/RECORD
