Metadata-Version: 2.1
Name: arraycontract
Version: 0.0.2
Summary: Check shape, ndim and dtype of tensor/ndarray of input of function
Home-page: https://github.com/cjwcommuny/array_contract
Author: cjwcommuny
Author-email: cjwcommuny@outlook.com
License: UNKNOWN
Platform: UNKNOWN
Classifier: Programming Language :: Python :: 3
Classifier: License :: OSI Approved :: MIT License
Classifier: Operating System :: OS Independent
Requires-Python: >=3.6
